MANIFEST.in
README
setup.py
webtail/__init__.py
webtail/webtail.py
webtail.egg-info/PKG-INFO
webtail.egg-info/SOURCES.txt
webtail.egg-info/dependency_links.txt
webtail.egg-info/entry_points.txt
webtail.egg-info/requires.txt
webtail.egg-info/top_level.txt
webtail.egg-info/zip-safe
webtail/static/css/bootstrap.min.css
webtail/static/js/bootstrap.min.js
webtail/static/js/jquery.min.js
webtail/templates/template.html