Metadata-Version: 1.1
Name: webtail
Version: 0.1b16
Summary: Tornado-based log viewer
Home-page: https://bitbucket.org/uptimebox/webtail
Author: Mikhail Lukyanchenko
Author-email: ml@uptimebox.ru
License: BSD License
Platform: UNKNOWN
Classifier: Development Status :: 4 - Beta
Classifier: Environment :: Web Environment
Classifier: Intended Audience :: Developers
Classifier: License :: OSI Approved :: BSD License
Classifier: Programming Language :: Python
Classifier: Topic :: Internet :: WWW/HTTP
